{"cameraMode":{"drawMode":0,"name":"Shaded","section":"Shading Mode"},"sceneLighting":true,"audioPlay":false,"sceneViewState":{"m_AlwaysRefresh":false,"showFog":true,"showSkybox":true,"showFlares":true,"showImageEffects":true,"showParticleSystems":true,"showVisualEffectGraphs":true,"m_FxEnabled":true},"in2DMode":false,"pivot":{"x":0.0,"y":3.6000001430511476,"z":-3.0},"rotation":{"x":-0.3732997477054596,"y":0.03254936635494232,"z":-0.013108430430293084,"w":-0.9270519614219666},"size":7.2621235847473148,"orthographic":false}